nnotes/__init__.py
nnotes/nnotes.py
nnotes/defaults/notebooks.txt
nnotes/defaults/settings.ini
nnotes-0.0.3.dist-info/LICENSE
nnotes-0.0.3.dist-info/METADATA
nnotes-0.0.3.dist-info/WHEEL
nnotes-0.0.3.dist-info/entry_points.txt
nnotes-0.0.3.dist-info/top_level.txt
nnotes-0.0.3.dist-info/RECORD
