Metadata-Version: 2.1
Name: nnotes
Version: 0.0.3
Summary: A cli notetaking tool
Home-page: https://github.com/wbwqq/nnotes
Author: wbwqq
License: UNKNOWN
Project-URL: Bug Tracker, https://github.com/wbwqq/nnotes/issues
Platform: UNKNOWN
Classifier: Programming Language :: Python :: 3
Classifier: License :: OSI Approved :: GNU General Public License v3 (GPLv3)
Classifier: Operating System :: OS Independent
Requires-Python: >=3.6
License-File: LICENSE
Requires-Dist: miniparser (==0.0.8)
